kvdb/__init__.py
kvdb/backoff.py
kvdb/client.py
kvdb/errors.py
kvdb/version.py
kvdb/components/__init__.py
kvdb/components/client.py
kvdb/components/cluster.py
kvdb/components/connection.py
kvdb/components/connection_pool.py
kvdb/components/lock.py
kvdb/components/persistence.py
kvdb/components/pipeline.py
kvdb/components/pubsub.py
kvdb/components/session.py
kvdb/components/session.pyi
kvdb/configs/__init__.py
kvdb/configs/base.py
kvdb/configs/caching.py
kvdb/configs/core.py
kvdb/configs/defaults.py
kvdb/configs/main.py
kvdb/configs/tasks.py
kvdb/configs/types.py
kvdb/io/__init__.py
kvdb/io/encoder.py
kvdb/io/cachify/__init__.py
kvdb/io/cachify/base.py
kvdb/io/cachify/cache.py
kvdb/io/cachify/main.py
kvdb/io/compression/__init__.py
kvdb/io/compression/_gzip.py
kvdb/io/compression/_lz4.py
kvdb/io/compression/_lzma.py
kvdb/io/compression/_zlib.py
kvdb/io/compression/_zstd.py
kvdb/io/compression/base.py
kvdb/io/serializers/__init__.py
kvdb/io/serializers/_json.py
kvdb/io/serializers/_msgpack.py
kvdb/io/serializers/_pickle.py
kvdb/io/serializers/base.py
kvdb/io/serializers/utils.py
kvdb/tasks/__init__.py
kvdb/tasks/abstract.py
kvdb/tasks/cli.py
kvdb/tasks/main.py
kvdb/tasks/queue.py
kvdb/tasks/spawn.py
kvdb/tasks/static.py
kvdb/tasks/tasks.py
kvdb/tasks/types.py
kvdb/tasks/utils.py
kvdb/tasks/worker.py
kvdb/tasks/wraps.py
kvdb/types/__init__.py
kvdb/types/base.py
kvdb/types/common.py
kvdb/types/contexts.py
kvdb/types/generic.py
kvdb/types/jobs.py
kvdb/types/mixins.py
kvdb/utils/__init__.py
kvdb/utils/cron.py
kvdb/utils/helpers.py
kvdb/utils/lazy.py
kvdb/utils/logs.py
kvdb/utils/patching.py
kvdb/utils/pool.py
kvdb/utils/retry.py
kvdb_py-0.0.2.dist-info/LICENSE
kvdb_py-0.0.2.dist-info/METADATA
kvdb_py-0.0.2.dist-info/WHEEL
kvdb_py-0.0.2.dist-info/entry_points.txt
kvdb_py-0.0.2.dist-info/top_level.txt
kvdb_py-0.0.2.dist-info/RECORD
