Metadata-Version: 2.1
Name: kvdb-py
Version: 0.0.2
Summary: Key-Value DB Python Client Abstraction built on top of Redis
Home-page: https://github.com/trisongz/kvdb-py
Author: Tri Songz
Author-email: ts@growthengineai.com
License: MIT Style
Classifier: Intended Audience :: Developers
Classifier: License :: OSI Approved :: MIT License
Classifier: Programming Language :: Python :: 3.7
Classifier: Topic :: Software Development :: Libraries
License-File: LICENSE
Requires-Dist: anyio
Requires-Dist: pydantic
Requires-Dist: pydantic-settings
Requires-Dist: croniter
Requires-Dist: tenacity
Requires-Dist: backoff
Requires-Dist: redis
Requires-Dist: hiredis
Requires-Dist: xxhash
Requires-Dist: makefun
Requires-Dist: lazyops >=0.2.69
Requires-Dist: typer
Requires-Dist: typing-extensions ; python_version < "3.8"
Provides-Extra: serialization
Requires-Dist: pysimdjson ; extra == 'serialization'
Requires-Dist: cloudpickle ; extra == 'serialization'
Requires-Dist: zstd ; extra == 'serialization'
